model_optimization_workflow/__init__.py
model_optimization_workflow/configs/__init__.py
model_optimization_workflow/configs/config_loader.py
model_optimization_workflow/configs/default_workflow_config.yaml
model_optimization_workflow/model_container/__init__.py
model_optimization_workflow/model_container/model_container.py
model_optimization_workflow/model_container/test_model_container.py
model_optimization_workflow/optimizer/__init__.py
model_optimization_workflow/optimizer/binary_class_score_calculator.py
model_optimization_workflow/optimizer/global_hyperparameter_optimizer.py
model_optimization_workflow/optimizer/score_calculator.py
model_optimization_workflow/provider/__init__.py
model_optimization_workflow/provider/datasets_provider.py
model_optimization_workflow/report/__init__.py
model_optimization_workflow/report/all_runs_validation_report.py
model_optimization_workflow/report/report.py
model_optimization_workflow/report/validations_report_manager.py
model_optimization_workflow/report/visualization_filter.py
model_optimization_workflow/report/сross_params_distribution_report.py
model_optimization_workflow/tests/__init__.py
model_optimization_workflow/tests/main.py
model_optimization_workflow/workflow/__init__.py
model_optimization_workflow/workflow/folds_generator.py
model_optimization_workflow/workflow/folds_window.py
model_optimization_workflow/workflow/run_processor.py
model_optimization_workflow/workflow/workflow_processor.py
model_optimization_workflow-0.5.8.dist-info/METADATA
model_optimization_workflow-0.5.8.dist-info/WHEEL
model_optimization_workflow-0.5.8.dist-info/top_level.txt
model_optimization_workflow-0.5.8.dist-info/RECORD
