Metadata-Version: 2.1
Name: model_optimization_workflow
Version: 0.5.8
Summary: Model optimization workflow
Author: Maksym Usanin
Author-email: usanin.max@gmail.com
Classifier: Programming Language :: Python :: 3
Classifier: Programming Language :: Python :: 3.11
Classifier: Operating System :: OS Independent
Requires-Python: >=3.11
Requires-Dist: matplotlib
Requires-Dist: seaborn
Requires-Dist: optuna~=4.0.0
Requires-Dist: pyyaml
Requires-Dist: market-data-assembler~=1.2.2
Requires-Dist: scikit-learn
Requires-Dist: plotly
Requires-Dist: openpyxl
